{"cameraMode":{"drawMode":0,"name":"Shaded","section":"Shading Mode"},"sceneLighting":false,"audioPlay":false,"sceneViewState":{"m_AlwaysRefresh":false,"showFog":true,"showSkybox":false,"showFlares":true,"showImageEffects":true,"showParticleSystems":true,"showVisualEffectGraphs":true,"m_FxEnabled":true},"in2DMode":false,"pivot":{"x":-0.15720653533935548,"y":0.027630865573883058,"z":0.04800820350646973},"rotation":{"x":0.3886628746986389,"y":-0.22706939280033112,"z":0.09945062547922135,"w":0.8874084949493408},"size":0.9576631784439087,"orthographic":false}